papysql/__init__.py
papysql/papysql.py
test/__init__.py
test/test_myfunctions.py
papysql-0.2.6.dist-info/LICENSE.txt
papysql-0.2.6.dist-info/METADATA
papysql-0.2.6.dist-info/WHEEL
papysql-0.2.6.dist-info/top_level.txt
papysql-0.2.6.dist-info/RECORD
