Metadata-Version: 2.1
Name: papysql
Version: 0.2.6
Author: Francesco Gualdi
License: GPL
License-File: LICENSE.txt
